mf4processor/__init__.py
mf4processor/processor.py
mf4processor-2.0.1.dist-info/LICENSE
mf4processor-2.0.1.dist-info/METADATA
mf4processor-2.0.1.dist-info/WHEEL
mf4processor-2.0.1.dist-info/top_level.txt
mf4processor-2.0.1.dist-info/RECORD
