Metadata-Version: 2.1
Name: mf4processor
Version: 2.0.1
Summary: A Python library for processing MF4 files
Home-page: https://github.com/varshithvhegde/mf4processor
Author: Varshith V Hegde
Author-email: varshithvh@gmail.com
License: UNKNOWN
Platform: UNKNOWN
Classifier: Programming Language :: Python :: 3
Classifier: License :: OSI Approved :: MIT License
Classifier: Operating System :: OS Independent
Requires-Python: >=3.6
Requires-Dist: asammdf
Requires-Dist: pandas
Requires-Dist: numpy
